{
    "config": {
        "iso": "2020-08-31T00:55:44.013664",
        "timestamp": 1598835344.013664
    },
    "directory_structure": {
        "iso": "2020-08-31T00:55:44.168465",
        "timestamp": 1598835344.168465
    },
    "iana": {
        "iso": "2020-08-30T11:31:26.991042",
        "timestamp": 1598787086.991042
    },
    "psl": {
        "iso": "2020-08-30T11:31:27.062723",
        "timestamp": 1598787087.062723
    },
    "user_agents": {
        "iso": "2020-08-30T11:31:27.120854",
        "timestamp": 1598787087.120854
    }
}