{
    "config": {
        "iso": "2020-09-05T00:10:29.592958",
        "timestamp": 1599264629.592958
    },
    "directory_structure": {
        "iso": "2020-09-05T00:10:29.726875",
        "timestamp": 1599264629.726875
    },
    "iana": {
        "iso": "2020-09-04T13:24:37.674696",
        "timestamp": 1599225877.674696
    },
    "psl": {
        "iso": "2020-09-04T13:24:37.846315",
        "timestamp": 1599225877.846315
    },
    "user_agents": {
        "iso": "2020-09-04T13:24:37.912722",
        "timestamp": 1599225877.912722
    }
}