{
    "config": {
        "iso": "2020-02-11T02:52:22.821885",
        "timestamp": 1581389542.821885
    },
    "db_type_mariadb": {
        "iso": "2020-03-10T02:58:38.644484",
        "timestamp": 1583809118.644484
    },
    "directory_structure": {
        "iso": "2020-02-11T02:52:23.195240",
        "timestamp": 1581389543.19524
    },
    "iana": {
        "iso": "2020-03-10T02:54:07.793667",
        "timestamp": 1583808847.793667
    },
    "psl": {
        "iso": "2020-03-10T02:54:08.083652",
        "timestamp": 1583808848.083652
    },
    "user_agents": {
        "iso": "2020-03-10T02:54:08.236731",
        "timestamp": 1583808848.236731
    }
}